{"035c624d-a85f-4faa":{"x":0,"y":-2533,"width":1349,"height":3655.390625,"top":-2533,"right":1349,"bottom":1122.390625,"left":0},"6fff43fb-0319-44cc":{"x":0,"y":-2533,"width":1349,"height":3655.390625,"top":-2533,"right":1349,"bottom":1122.390625,"left":0},"8bfee5e4-567d-4a59":{"x":0,"y":-2533,"width":1349,"height":3636.5,"top":-2533,"right":1349,"bottom":1103.5,"left":0},"f1e6242b-302f-493a":{"x":0,"y":-2533,"width":1349,"height":3636.5,"top":-2533,"right":1349,"bottom":1103.5,"left":0},"c88c39dc-18e2-439c":{"x":0,"y":-2533,"width":1349,"height":3636.5,"top":-2533,"right":1349,"bottom":1103.5,"left":0},"7663091f-ee5b-4c74":{"x":0,"y":0,"width":1349,"height":79,"top":0,"right":1349,"bottom":79,"left":0},"eb3e6901-001a-4657":{"x":0,"y":0,"width":1349,"height":79,"top":0,"right":1349,"bottom":79,"left":0},"687ca8ad-d3b7-41fc":{"x":0,"y":0,"width":153,"height":78,"top":0,"right":153,"bottom":78,"left":0},"28adb22e-6269-4ffd":{"x":25,"y":18.5,"width":128,"height":36,"top":18.5,"right":153,"bottom":54.5,"left":25},"c71e6f2b-e3db-46f7":{"x":153,"y":0,"width":1082,"height":78,"top":0,"right":1235,"bottom":78,"left":153},"07fede3a-485b-46a9":{"x":153,"y":0,"width":1082,"height":78,"top":0,"right":1235,"bottom":78,"left":153},"8ae77236-2089-4d91":{"x":153,"y":0,"width":1082,"height":78,"top":0,"right":1235,"bottom":78,"left":153},"4526ba67-3488-48c1":{"x":161,"y":14.625,"width":145.390625,"height":48.75,"top":14.625,"right":306.390625,"bottom":63.375,"left":161},"ee921251-f8a9-41f9":{"x":161,"y":14.625,"width":145.390625,"height":48.75,"top":14.625,"right":306.390625,"bottom":63.375,"left":161},"56ef108e-3e24-475e":{"x":161,"y":14.625,"width":145.390625,"height":48.75,"top":14.625,"right":306.390625,"bottom":63.375,"left":161},"bc0b2db3-87b3-40fb":{"x":161,"y":14.625,"width":145.390625,"height":48.75,"top":14.625,"right":306.390625,"bottom":63.375,"left":161},"d266e384-d7a9-47e0":{"x":161,"y":14.625,"width":145.390625,"height":48.75,"top":14.625,"right":306.390625,"bottom":63.375,"left":161},"baf77c44-170f-4934":{"x":161,"y":14.625,"width":145.390625,"height":48.75,"top":14.625,"right":306.390625,"bottom":63.375,"left":161},"82ac3864-3c35-484c":{"x":161,"y":14.625,"width":145.390625,"height":48.75,"top":14.625,"right":306.390625,"bottom":63.375,"left":161},"30b03deb-ca65-4c3d":{"x":181,"y":29.625,"width":113.390625,"height":21.75,"top":29.625,"right":294.390625,"bottom":51.375,"left":181},"53d35bc7-20ad-4302":{"x":181,"y":29.625,"width":113.390625,"height":21.75,"top":29.625,"right":294.390625,"bottom":51.375,"left":181},"2d547fe4-0cd9-4391":{"x":181,"y":29.625,"width":97.390625,"height":21.75,"top":29.625,"right":278.390625,"bottom":51.375,"left":181},"9d08326b-2b02-4bb8":{"x":282.390625,"y":29.625,"width":12,"height":21.75,"top":29.625,"right":294.390625,"bottom":51.375,"left":282.390625},"8dd86ac4-2e3a-4f3c":{"x":282.390625,"y":34.5,"width":12,"height":12,"top":34.5,"right":294.390625,"bottom":46.5,"left":282.390625},"f78f87c4-653c-49ac":{"x":282.390625,"y":34.5,"width":12,"height":12,"top":34.5,"right":294.390625,"bottom":46.5,"left":282.390625},"1bfc1b14-6bca-460c":{"x":282.390625,"y":34.5,"width":12,"height":12,"top":34.5,"right":294.390625,"bottom":46.5,"left":282.390625},"f95127c8-ec28-45bb":{"x":322.390625,"y":19,"width":904.609375,"height":40,"top":19,"right":1227,"bottom":59,"left":322.390625},"b561f8e4-e0d6-4d45":{"x":322.390625,"y":19,"width":904.609375,"height":40,"top":19,"right":1227,"bottom":59,"left":322.390625},"480e9c46-e43e-4b48":{"x":322.390625,"y":19,"width":350,"height":40,"top":19,"right":672.390625,"bottom":59,"left":322.390625},"eda21fe7-8dd4-4ff2":{"x":322.390625,"y":19,"width":350,"height":40,"top":19,"right":672.390625,"bottom":59,"left":322.390625},"09147cfb-0db7-41ce":{"x":322.390625,"y":19,"width":44,"height":40,"top":19,"right":366.390625,"bottom":59,"left":322.390625},"94e62789-1d46-47c8":{"x":336.390625,"y":31,"width":16,"height":16,"top":31,"right":352.390625,"bottom":47,"left":336.390625},"f7b2e981-03b4-49e7":{"x":336.390625,"y":31,"width":16,"height":16,"top":31,"right":352.390625,"bottom":47,"left":336.390625},"2b481d35-c65e-4b36":{"x":336.390625,"y":31,"width":16,"height":16,"top":31,"right":352.390625,"bottom":47,"left":336.390625},"76d1ac05-3b7d-4ab4":{"x":1235,"y":0,"width":74,"height":78,"top":0,"right":1309,"bottom":78,"left":1235},"7d9ed801-4861-4a9d":{"x":1235,"y":7.5,"width":74,"height":63,"top":7.5,"right":1309,"bottom":70.5,"left":1235},"8e7355e1-8e68-4f31":{"x":1235,"y":7.5,"width":74,"height":63,"top":7.5,"right":1309,"bottom":70.5,"left":1235},"ae7a3379-6eae-4690":{"x":1235,"y":7.5,"width":74,"height":63,"top":7.5,"right":1309,"bottom":70.5,"left":1235},"2b8a8646-8de8-4196":{"x":1235,"y":7.5,"width":74,"height":63,"top":7.5,"right":1309,"bottom":70.5,"left":1235},"1c4fe57e-e9e7-48f3":{"x":1260,"y":27,"width":24,"height":24,"top":27,"right":1284,"bottom":51,"left":1260},"891ef3b8-cf82-4b54":{"x":1260,"y":27,"width":24,"height":24,"top":27,"right":1284,"bottom":51,"left":1260},"a06e1fd2-6a53-48ae":{"x":1260,"y":27,"width":24,"height":24,"top":27,"right":1284,"bottom":51,"left":1260},"e95cd965-42f4-4269":{"x":1260,"y":27,"width":24,"height":24,"top":27,"right":1284,"bottom":51,"left":1260},"9ae1ed23-7511-4437":{"x":1309,"y":0,"width":40,"height":78,"top":0,"right":1349,"bottom":78,"left":1309},"ca2690ed-47f6-4559":{"x":1309,"y":21,"width":24,"height":36,"top":21,"right":1333,"bottom":57,"left":1309},"33c2e63d-c7ce-4ab2":{"x":1309,"y":21,"width":24,"height":36,"top":21,"right":1333,"bottom":57,"left":1309},"f7e961a1-21db-46f6":{"x":1309,"y":27,"width":24,"height":24,"top":27,"right":1333,"bottom":51,"left":1309},"822bb90a-6c61-4411":{"x":1309,"y":27,"width":24,"height":24,"top":27,"right":1333,"bottom":51,"left":1309},"9c1ee5c8-f535-4577":{"x":1309,"y":27,"width":24,"height":24,"top":27,"right":1333,"bottom":51,"left":1309},"0aeb9569-c137-4215":{"x":0,"y":-2455,"width":1349,"height":3636.5,"top":-2455,"right":1349,"bottom":1181.5,"left":0},"3258851b-aba7-4d1d":{"x":0,"y":-2455,"width":1349,"height":3636.5,"top":-2455,"right":1349,"bottom":1181.5,"left":0},"1ef6d90f-b5e0-4bb0":{"x":0,"y":-2455,"width":1349,"height":3636.5,"top":-2455,"right":1349,"bottom":1181.5,"left":0},"31c41c55-95db-461a":{"x":0,"y":-2455,"width":1349,"height":3636.5,"top":-2455,"right":1349,"bottom":1181.5,"left":0},"eb59d328-7e13-46a7":{"x":0,"y":-2455,"width":1349,"height":3636.5,"top":-2455,"right":1349,"bottom":1181.5,"left":0},"2f096613-4dbf-4161":{"x":0,"y":-2455,"width":1349,"height":3636.5,"top":-2455,"right":1349,"bottom":1181.5,"left":0},"f65d8b4c-845e-432a":{"x":0,"y":-2455,"width":1349,"height":3636.5,"top":-2455,"right":1349,"bottom":1181.5,"left":0},"1d3ba936-98d1-4067":{"x":0,"y":-2455,"width":1349,"height":2920.375,"top":-2455,"right":1349,"bottom":465.375,"left":0},"211e4fa0-dfd7-4151":{"x":0,"y":-2455,"width":1349,"height":2920.375,"top":-2455,"right":1349,"bottom":465.375,"left":0},"407e8313-141f-45ae":{"x":0,"y":-2455,"width":1349,"height":2920.375,"top":-2455,"right":1349,"bottom":465.375,"left":0},"c41728d8-841e-432c":{"x":0,"y":-2455,"width":1349,"height":2920.375,"top":-2455,"right":1349,"bottom":465.375,"left":0},"c00515c8-e7ff-4f2c":{"x":0,"y":-2455,"width":1349,"height":2920.375,"top":-2455,"right":1349,"bottom":465.375,"left":0},"cd5cf494-9476-4b18":{"x":0,"y":78,"width":1349,"height":66.296875,"top":78,"right":1349,"bottom":144.296875,"left":0},"20cd3548-6322-4973":{"x":104.5,"y":94,"width":1140,"height":34.296875,"top":94,"right":1244.5,"bottom":128.296875,"left":104.5},"bf73eb49-d9eb-474c":{"x":104.5,"y":94,"width":1140,"height":34.296875,"top":94,"right":1244.5,"bottom":128.296875,"left":104.5},"d70025f5-0952-4da0":{"x":104.5,"y":94,"width":1140,"height":34.296875,"top":94,"right":1244.5,"bottom":128.296875,"left":104.5},"792e50ba-e5e6-4497":{"x":107.5,"y":94,"width":36,"height":36,"top":94,"right":143.5,"bottom":130,"left":107.5},"4e812cf8-ad84-4196":{"x":109.5,"y":96,"width":32,"height":32,"top":96,"right":141.5,"bottom":128,"left":109.5},"57a3122b-2328-4354":{"x":109.5,"y":96,"width":32,"height":32,"top":96,"right":141.5,"bottom":128,"left":109.5},"6912ba1f-4e1b-47e4":{"x":109.5,"y":96,"width":32,"height":32,"top":96,"right":141.5,"bottom":128,"left":109.5},"2b2e472d-1070-4e1f":{"x":104.5,"y":94,"width":957.140625,"height":34.296875,"top":94,"right":1061.640625,"bottom":128.296875,"left":104.5},"ddf139a5-2de6-43ec":{"x":104.5,"y":94,"width":135.0625,"height":34.296875,"top":94,"right":239.5625,"bottom":128.296875,"left":104.5},"88be84a8-0549-4d66":{"x":104.5,"y":94,"width":135.0625,"height":34.296875,"top":94,"right":239.5625,"bottom":128.296875,"left":104.5},"e9956201-b1e2-4169":{"x":104.5,"y":94,"width":135.0625,"height":34.296875,"top":94,"right":239.5625,"bottom":128.296875,"left":104.5},"9c85c22f-055d-47a9":{"x":121.5,"y":101,"width":101.0625,"height":20.296875,"top":101,"right":222.5625,"bottom":121.296875,"left":121.5},"2415c79f-d794-4c5e":{"x":251.5625,"y":94,"width":76.046875,"height":34.296875,"top":94,"right":327.609375,"bottom":128.296875,"left":251.5625},"a99a2633-5d2a-4e8a":{"x":251.5625,"y":94,"width":76.046875,"height":34.296875,"top":94,"right":327.609375,"bottom":128.296875,"left":251.5625},"0f650ce5-b5a1-411d":{"x":251.5625,"y":94,"width":76.046875,"height":34.296875,"top":94,"right":327.609375,"bottom":128.296875,"left":251.5625},"ba827628-46ac-4c64":{"x":268.5625,"y":101,"width":42.046875,"height":20.296875,"top":101,"right":310.609375,"bottom":121.296875,"left":268.5625},"53a6194b-7959-491e":{"x":339.609375,"y":94,"width":108.859375,"height":34.296875,"top":94,"right":448.46875,"bottom":128.296875,"left":339.609375},"d72cf7d4-e626-436f":{"x":339.609375,"y":94,"width":108.859375,"height":34.296875,"top":94,"right":448.46875,"bottom":128.296875,"left":339.609375},"a93b4aaa-4c73-4ede":{"x":339.609375,"y":94,"width":108.859375,"height":34.296875,"top":94,"right":448.46875,"bottom":128.296875,"left":339.609375},"d5991659-ab19-4828":{"x":356.609375,"y":101,"width":74.859375,"height":20.296875,"top":101,"right":431.46875,"bottom":121.296875,"left":356.609375},"c93a3c62-b023-4b65":{"x":460.46875,"y":94,"width":159.203125,"height":34.296875,"top":94,"right":619.671875,"bottom":128.296875,"left":460.46875},"376e4099-1749-44a3":{"x":460.46875,"y":94,"width":159.203125,"height":34.296875,"top":94,"right":619.671875,"bottom":128.296875,"left":460.46875},"ed43b4c6-99a4-43fc":{"x":460.46875,"y":94,"width":159.203125,"height":34.296875,"top":94,"right":619.671875,"bottom":128.296875,"left":460.46875},"0579a622-6015-43fe":{"x":477.46875,"y":101,"width":125.203125,"height":20.296875,"top":101,"right":602.671875,"bottom":121.296875,"left":477.46875},"41378a37-0bbe-4d1a":{"x":631.671875,"y":94,"width":139.21875,"height":34.296875,"top":94,"right":770.890625,"bottom":128.296875,"left":631.671875},"56fe1523-561d-4970":{"x":631.671875,"y":94,"width":139.21875,"height":34.296875,"top":94,"right":770.890625,"bottom":128.296875,"left":631.671875},"30eaed8d-a71f-4a70":{"x":631.671875,"y":94,"width":139.21875,"height":34.296875,"top":94,"right":770.890625,"bottom":128.296875,"left":631.671875},"ab66ff0e-2a02-4f5e":{"x":648.671875,"y":102.640625,"width":32,"height":17,"top":102.640625,"right":680.671875,"bottom":119.640625,"left":648.671875},"3e2ac993-63a0-4ff5":{"x":648.671875,"y":102.640625,"width":32,"height":17,"top":102.640625,"right":680.671875,"bottom":119.640625,"left":648.671875},"57ddc5e1-5f8b-4f99":{"x":684.671875,"y":101,"width":69.21875,"height":20.296875,"top":101,"right":753.890625,"bottom":121.296875,"left":684.671875},"0fccc9f1-de5b-4b13":{"x":782.890625,"y":94,"width":171.53125,"height":34.296875,"top":94,"right":954.421875,"bottom":128.296875,"left":782.890625},"db658171-b458-43af":{"x":782.890625,"y":94,"width":171.53125,"height":34.296875,"top":94,"right":954.421875,"bottom":128.296875,"left":782.890625},"6c4d7838-91ad-4a66":{"x":782.890625,"y":94,"width":171.53125,"height":34.296875,"top":94,"right":954.421875,"bottom":128.296875,"left":782.890625},"e4610bc9-7c25-4da1":{"x":799.890625,"y":101,"width":137.53125,"height":20.296875,"top":101,"right":937.421875,"bottom":121.296875,"left":799.890625},"31430ad5-732c-4d6f":{"x":966.421875,"y":94,"width":95.21875,"height":34.296875,"top":94,"right":1061.640625,"bottom":128.296875,"left":966.421875},"21c2f470-d82b-4b51":{"x":966.421875,"y":94,"width":95.21875,"height":34.296875,"top":94,"right":1061.640625,"bottom":128.296875,"left":966.421875},"4d29431e-0989-4259":{"x":966.421875,"y":94,"width":95.21875,"height":34.296875,"top":94,"right":1061.640625,"bottom":128.296875,"left":966.421875},"f94b2144-58f7-433f":{"x":983.421875,"y":101,"width":61.21875,"height":20.296875,"top":101,"right":1044.640625,"bottom":121.296875,"left":983.421875},"958a66d3-0fea-4c52":{"x":1205.5,"y":94,"width":36,"height":36,"top":94,"right":1241.5,"bottom":130,"left":1205.5},"0c56cd45-f1ee-49c7":{"x":1207.5,"y":96,"width":32,"height":32,"top":96,"right":1239.5,"bottom":128,"left":1207.5},"f1c68c29-13c6-4e28":{"x":1207.5,"y":96,"width":32,"height":32,"top":96,"right":1239.5,"bottom":128,"left":1207.5},"34098fe0-54a6-4b75":{"x":1207.5,"y":96,"width":32,"height":32,"top":96,"right":1239.5,"bottom":128,"left":1207.5},"7462f237-92c5-480e":{"x":0,"y":-2161.40625,"width":1349,"height":2626.78125,"top":-2161.40625,"right":1349,"bottom":465.375,"left":0},"e83b0d14-747b-45a0":{"x":0,"y":-2161.40625,"width":1349,"height":2626.78125,"top":-2161.40625,"right":1349,"bottom":465.375,"left":0},"e5ddbd3e-8f46-4fc6":{"x":0,"y":-2161.40625,"width":1349,"height":2626.78125,"top":-2161.40625,"right":1349,"bottom":465.375,"left":0},"29995e3e-96fd-474b":{"x":0,"y":-2161.40625,"width":1349,"height":2626.78125,"top":-2161.40625,"right":1349,"bottom":465.375,"left":0},"2e3aa315-210d-4ab7":{"x":0,"y":-2161.40625,"width":1349,"height":2626.78125,"top":-2161.40625,"right":1349,"bottom":465.375,"left":0},"fef07eb8-52b1-4c0a":{"x":0,"y":-2161.40625,"width":1349,"height":2626.78125,"top":-2161.40625,"right":1349,"bottom":465.375,"left":0},"a4d683a9-1b84-4932":{"x":0,"y":-2161.40625,"width":1349,"height":2626.78125,"top":-2161.40625,"right":1349,"bottom":465.375,"left":0},"3ffdf308-c96e-42cf":{"x":104.5,"y":-2161.40625,"width":1140,"height":2476.1875,"top":-2161.40625,"right":1244.5,"bottom":314.78125,"left":104.5},"09cde144-ec61-4efb":{"x":104.5,"y":-2161.40625,"width":1140,"height":2476.1875,"top":-2161.40625,"right":1244.5,"bottom":314.78125,"left":104.5},"f9a6dfc6-b293-4615":{"x":104.5,"y":-2161.40625,"width":1140,"height":2476.1875,"top":-2161.40625,"right":1244.5,"bottom":314.78125,"left":104.5},"be0f9040-6656-4cda":{"x":104.5,"y":-2120.21875,"width":1140,"height":2435,"top":-2120.21875,"right":1244.5,"bottom":314.78125,"left":104.5},"30f6d0ee-58c5-4c4b":{"x":104.5,"y":-2120.21875,"width":1140,"height":2435,"top":-2120.21875,"right":1244.5,"bottom":314.78125,"left":104.5},"9a39d4e2-8eeb-4f60":{"x":104.5,"y":-2120.21875,"width":1140,"height":2435,"top":-2120.21875,"right":1244.5,"bottom":314.78125,"left":104.5},"8e33a039-1d7e-4111":{"x":104.5,"y":-33.21875,"width":1140,"height":116,"top":-33.21875,"right":1244.5,"bottom":82.78125,"left":104.5},"8bbec41b-e80a-4c0c":{"x":104.5,"y":-33.21875,"width":1140,"height":116,"top":-33.21875,"right":1244.5,"bottom":82.78125,"left":104.5},"13009059-86aa-4402":{"x":104.5,"y":-33.21875,"width":1140,"height":116,"top":-33.21875,"right":1244.5,"bottom":82.78125,"left":104.5},"bf39a2ae-26a3-413b":{"x":104.5,"y":-32.21875,"width":1140,"height":115,"top":-32.21875,"right":1244.5,"bottom":82.78125,"left":104.5},"73d236ec-6f38-40a7":{"x":128.5,"y":-17.21875,"width":546,"height":90,"top":-17.21875,"right":674.5,"bottom":72.78125,"left":128.5},"14512951-bcbb-416c":{"x":128.5,"y":-17.21875,"width":546,"height":90,"top":-17.21875,"right":674.5,"bottom":72.78125,"left":128.5},"cd287e84-32c5-4105":{"x":128.5,"y":-17.21875,"width":90,"height":90,"top":-17.21875,"right":218.5,"bottom":72.78125,"left":128.5},"0d366e38-02ba-42ce":{"x":128.5,"y":-17.21875,"width":90,"height":90,"top":-17.21875,"right":218.5,"bottom":72.78125,"left":128.5},"f0cd74ed-1710-4048":{"x":218.5,"y":-17.21875,"width":456,"height":90,"top":-17.21875,"right":674.5,"bottom":72.78125,"left":218.5},"c301f5ff-360b-4025":{"x":238.5,"y":-17.21875,"width":426,"height":51.921875,"top":-17.21875,"right":664.5,"bottom":34.703125,"left":238.5},"68b1004a-bfde-4b3c":{"x":238.5,"y":-17.21875,"width":426,"height":43.921875,"top":-17.21875,"right":664.5,"bottom":26.703125,"left":238.5},"7cbb6b8b-86f6-4b83":{"x":238.5,"y":-17.21875,"width":426,"height":22.53125,"top":-17.21875,"right":664.5,"bottom":5.3125,"left":238.5},"b906081b-d325-49ee":{"x":238.5,"y":-17.21875,"width":426,"height":22.53125,"top":-17.21875,"right":664.5,"bottom":5.3125,"left":238.5},"ebcefbe8-c721-4e32":{"x":238.5,"y":9.3125,"width":426,"height":17.390625,"top":9.3125,"right":664.5,"bottom":26.703125,"left":238.5},"fdb434d6-db91-44b3":{"x":238.5,"y":9.3125,"width":73.46875,"height":17.390625,"top":9.3125,"right":311.96875,"bottom":26.703125,"left":238.5},"0e28629a-c450-4063":{"x":238.5,"y":9.3125,"width":40,"height":17.390625,"top":9.3125,"right":278.5,"bottom":26.703125,"left":238.5},"a45e9078-959b-4be1":{"x":238.5,"y":9.5,"width":32,"height":17,"top":9.5,"right":270.5,"bottom":26.5,"left":238.5},"e8cfb283-9ca6-457c":{"x":238.5,"y":9.5,"width":32,"height":17,"top":9.5,"right":270.5,"bottom":26.5,"left":238.5},"61887c66-b83a-43be":{"x":278.5,"y":9.3125,"width":33.46875,"height":17.390625,"top":9.3125,"right":311.96875,"bottom":26.703125,"left":278.5},"da17b97b-4d4f-46dd":{"x":278.5,"y":10.3125,"width":33.46875,"height":14,"top":10.3125,"right":311.96875,"bottom":24.3125,"left":278.5},"9d234bef-8f7f-42d1":{"x":674.5,"y":-17.21875,"width":546,"height":90,"top":-17.21875,"right":1220.5,"bottom":72.78125,"left":674.5},"a1fea300-1700-480b":{"x":674.5,"y":-17.21875,"width":546,"height":46.828125,"top":-17.21875,"right":1220.5,"bottom":29.609375,"left":674.5},"95a109ed-bc1e-4ab8":{"x":811,"y":-17.21875,"width":136.5,"height":46.828125,"top":-17.21875,"right":947.5,"bottom":29.609375,"left":811},"72a8c755-ceb3-4be9":{"x":811,"y":-13.953125,"width":83.171875,"height":40.296875,"top":-13.953125,"right":894.171875,"bottom":26.34375,"left":811},"317753c9-84fd-4871":{"x":811,"y":-13.953125,"width":83.171875,"height":40.296875,"top":-13.953125,"right":894.171875,"bottom":26.34375,"left":811},"ef16e42d-8666-4ae1":{"x":811,"y":-13.953125,"width":83.171875,"height":40.296875,"top":-13.953125,"right":894.171875,"bottom":26.34375,"left":811},"6d4aac91-46ac-45e1":{"x":811,"y":-13.953125,"width":83.171875,"height":40.296875,"top":-13.953125,"right":894.171875,"bottom":26.34375,"left":811},"5af88728-7c61-440a":{"x":812.578125,"y":-13.953125,"width":80,"height":20,"top":-13.953125,"right":892.578125,"bottom":6.046875,"left":812.578125},"291e2668-8fbc-41be":{"x":812.578125,"y":-13.953125,"width":80,"height":16,"top":-13.953125,"right":892.578125,"bottom":2.046875,"left":812.578125},"fa9933ba-eab5-4a67":{"x":811,"y":6.046875,"width":83.171875,"height":20.296875,"top":6.046875,"right":894.171875,"bottom":26.34375,"left":811},"0d4aad41-bf16-44ac":{"x":947.5,"y":-17.21875,"width":136.5,"height":46.828125,"top":-17.21875,"right":1084,"bottom":29.609375,"left":947.5},"57ee606f-b825-4165":{"x":947.5,"y":-17.21875,"width":136.5,"height":46.828125,"top":-17.21875,"right":1084,"bottom":29.609375,"left":947.5},"7f204d26-6ddd-45fd":{"x":947.5,"y":-17.21875,"width":136.5,"height":44.53125,"top":-17.21875,"right":1084,"bottom":27.3125,"left":947.5},"51bc5d10-7b33-422b":{"x":947.5,"y":-17.21875,"width":136.5,"height":43.53125,"top":-17.21875,"right":1084,"bottom":26.3125,"left":947.5},"8368a22c-5bfb-4bcc":{"x":947.5,"y":-17.21875,"width":136.5,"height":43.53125,"top":-17.21875,"right":1084,"bottom":26.3125,"left":947.5},"56e874c9-fadf-45ff":{"x":947.5,"y":-17.21875,"width":136.5,"height":22.53125,"top":-17.21875,"right":1084,"bottom":5.3125,"left":947.5},"2d94a6df-97f9-44a2":{"x":1050.234375,"y":12.3125,"width":21.765625,"height":14,"top":12.3125,"right":1072,"bottom":26.3125,"left":1050.234375},"a3028350-7c99-4817":{"x":1084,"y":-13.203125,"width":136.5,"height":38.78125,"top":-13.203125,"right":1220.5,"bottom":25.578125,"left":1084},"10e2f799-1a78-4347":{"x":1084,"y":-13.203125,"width":136.5,"height":38.78125,"top":-13.203125,"right":1220.5,"bottom":25.578125,"left":1084},"96f4a548-93e4-420b":{"x":1084,"y":-13.203125,"width":136.5,"height":17.390625,"top":-13.203125,"right":1220.5,"bottom":4.1875,"left":1084},"47df9579-aa83-4e0b":{"x":1084,"y":-13.203125,"width":136.5,"height":17.390625,"top":-13.203125,"right":1220.5,"bottom":4.1875,"left":1084},"0ed6f277-21f3-42c6":{"x":1084,"y":8.1875,"width":136.5,"height":17.390625,"top":8.1875,"right":1220.5,"bottom":25.578125,"left":1084},"8d69dd14-712f-4ad6":{"x":1084,"y":8.1875,"width":136.5,"height":17.390625,"top":8.1875,"right":1220.5,"bottom":25.578125,"left":1084},"e6f90698-2046-436d":{"x":104.5,"y":82.78125,"width":1140,"height":116,"top":82.78125,"right":1244.5,"bottom":198.78125,"left":104.5},"d81c7fad-a006-4acd":{"x":104.5,"y":82.78125,"width":1140,"height":116,"top":82.78125,"right":1244.5,"bottom":198.78125,"left":104.5},"5b986709-a4b7-482c":{"x":104.5,"y":82.78125,"width":1140,"height":116,"top":82.78125,"right":1244.5,"bottom":198.78125,"left":104.5},"dceb2490-4037-450d":{"x":104.5,"y":83.78125,"width":1140,"height":115,"top":83.78125,"right":1244.5,"bottom":198.78125,"left":104.5},"aa41bb3a-1b49-4ae3":{"x":128.5,"y":98.78125,"width":546,"height":90,"top":98.78125,"right":674.5,"bottom":188.78125,"left":128.5},"b6ad4453-10d0-411e":{"x":128.5,"y":98.78125,"width":546,"height":90,"top":98.78125,"right":674.5,"bottom":188.78125,"left":128.5},"8b4c55d3-637c-4c5e":{"x":128.5,"y":98.78125,"width":90,"height":90,"top":98.78125,"right":218.5,"bottom":188.78125,"left":128.5},"d7c21aab-9300-42b7":{"x":128.5,"y":98.78125,"width":90,"height":90,"top":98.78125,"right":218.5,"bottom":188.78125,"left":128.5},"7a080977-e12f-48c0":{"x":218.5,"y":98.78125,"width":456,"height":90,"top":98.78125,"right":674.5,"bottom":188.78125,"left":218.5},"203ecd66-7ef5-4990":{"x":238.5,"y":98.78125,"width":426,"height":51.921875,"top":98.78125,"right":664.5,"bottom":150.703125,"left":238.5},"0c8699d7-62b3-4439":{"x":238.5,"y":98.78125,"width":426,"height":43.921875,"top":98.78125,"right":664.5,"bottom":142.703125,"left":238.5},"d49bd61b-6a8e-4837":{"x":238.5,"y":98.78125,"width":426,"height":22.53125,"top":98.78125,"right":664.5,"bottom":121.3125,"left":238.5},"6028fe12-281a-4d86":{"x":238.5,"y":98.78125,"width":426,"height":22.53125,"top":98.78125,"right":664.5,"bottom":121.3125,"left":238.5},"13e9ba4c-7a0c-4d60":{"x":238.5,"y":125.3125,"width":426,"height":17.390625,"top":125.3125,"right":664.5,"bottom":142.703125,"left":238.5},"d1adb66a-4ab1-4667":{"x":238.5,"y":125.3125,"width":95.375,"height":17.390625,"top":125.3125,"right":333.875,"bottom":142.703125,"left":238.5},"ee6f862b-82df-422c":{"x":238.5,"y":125.3125,"width":40,"height":17.390625,"top":125.3125,"right":278.5,"bottom":142.703125,"left":238.5},"ca7240d4-98c9-4979":{"x":238.5,"y":125.5,"width":32,"height":17,"top":125.5,"right":270.5,"bottom":142.5,"left":238.5},"c861a1ba-122d-44f8":{"x":238.5,"y":125.5,"width":32,"height":17,"top":125.5,"right":270.5,"bottom":142.5,"left":238.5},"a3b4c53b-b5c0-406a":{"x":278.5,"y":125.3125,"width":55.375,"height":17.390625,"top":125.3125,"right":333.875,"bottom":142.703125,"left":278.5},"f2c131d3-416a-4d3f":{"x":278.5,"y":126.3125,"width":55.375,"height":14,"top":126.3125,"right":333.875,"bottom":140.3125,"left":278.5},"f642c844-9cb3-4c8e":{"x":674.5,"y":98.78125,"width":546,"height":90,"top":98.78125,"right":1220.5,"bottom":188.78125,"left":674.5},"1e082814-cd72-4139":{"x":674.5,"y":98.78125,"width":546,"height":46.828125,"top":98.78125,"right":1220.5,"bottom":145.609375,"left":674.5},"4087a5b5-be11-43f0":{"x":811,"y":98.78125,"width":136.5,"height":46.828125,"top":98.78125,"right":947.5,"bottom":145.609375,"left":811},"32db9168-9209-446a":{"x":811,"y":102.046875,"width":81.015625,"height":40.296875,"top":102.046875,"right":892.015625,"bottom":142.34375,"left":811},"9a180f56-88e2-4726":{"x":811,"y":102.046875,"width":81.015625,"height":40.296875,"top":102.046875,"right":892.015625,"bottom":142.34375,"left":811},"a9212b12-a66c-4be9":{"x":811,"y":102.046875,"width":81.015625,"height":40.296875,"top":102.046875,"right":892.015625,"bottom":142.34375,"left":811},"9a9533a9-bfe8-4d75":{"x":811,"y":102.046875,"width":81.015625,"height":40.296875,"top":102.046875,"right":892.015625,"bottom":142.34375,"left":811},"b9f36c05-4dd9-46eb":{"x":811.5,"y":102.046875,"width":80,"height":20,"top":102.046875,"right":891.5,"bottom":122.046875,"left":811.5},"636fff57-1265-4e7e":{"x":811.5,"y":102.046875,"width":80,"height":16,"top":102.046875,"right":891.5,"bottom":118.046875,"left":811.5},"05399876-ef2e-4d3d":{"x":811,"y":122.046875,"width":81.015625,"height":20.296875,"top":122.046875,"right":892.015625,"bottom":142.34375,"left":811},"38608800-127d-4c7a":{"x":947.5,"y":98.78125,"width":136.5,"height":46.828125,"top":98.78125,"right":1084,"bottom":145.609375,"left":947.5},"ce360a82-6618-4727":{"x":947.5,"y":98.78125,"width":136.5,"height":46.828125,"top":98.78125,"right":1084,"bottom":145.609375,"left":947.5},"3d97f1fa-a791-446b":{"x":947.5,"y":98.78125,"width":136.5,"height":44.53125,"top":98.78125,"right":1084,"bottom":143.3125,"left":947.5},"aa54ab9c-b4dd-42f3":{"x":947.5,"y":98.78125,"width":136.5,"height":43.53125,"top":98.78125,"right":1084,"bottom":142.3125,"left":947.5},"6103e901-278a-45c8":{"x":947.5,"y":98.78125,"width":136.5,"height":43.53125,"top":98.78125,"right":1084,"bottom":142.3125,"left":947.5},"0ebb1541-d324-4768":{"x":947.5,"y":98.78125,"width":136.5,"height":22.53125,"top":98.78125,"right":1084,"bottom":121.3125,"left":947.5},"0d3dfce1-52ce-457c":{"x":1050.234375,"y":128.3125,"width":21.765625,"height":14,"top":128.3125,"right":1072,"bottom":142.3125,"left":1050.234375},"519d6fc9-4ac7-4a65":{"x":1084,"y":113.5,"width":136.5,"height":17.390625,"top":113.5,"right":1220.5,"bottom":130.890625,"left":1084},"2e8abf5c-8244-4ac8":{"x":1084,"y":113.5,"width":136.5,"height":17.390625,"top":113.5,"right":1220.5,"bottom":130.890625,"left":1084},"e68daeb7-6f1c-4fdb":{"x":1084,"y":113.5,"width":136.5,"height":17.390625,"top":113.5,"right":1220.5,"bottom":130.890625,"left":1084},"a891a01b-eaef-4183":{"x":1084,"y":113.5,"width":136.5,"height":17.390625,"top":113.5,"right":1220.5,"bottom":130.890625,"left":1084},"f5fdd86a-7180-4f6e":{"x":104.5,"y":198.78125,"width":1140,"height":116,"top":198.78125,"right":1244.5,"bottom":314.78125,"left":104.5},"bddc5862-430c-4fe2":{"x":104.5,"y":198.78125,"width":1140,"height":116,"top":198.78125,"right":1244.5,"bottom":314.78125,"left":104.5},"2eed7456-42b3-4009":{"x":104.5,"y":198.78125,"width":1140,"height":116,"top":198.78125,"right":1244.5,"bottom":314.78125,"left":104.5},"161c31fd-3835-4f12":{"x":104.5,"y":199.78125,"width":1140,"height":115,"top":199.78125,"right":1244.5,"bottom":314.78125,"left":104.5},"9c74fa6e-ce17-4880":{"x":128.5,"y":214.78125,"width":546,"height":90,"top":214.78125,"right":674.5,"bottom":304.78125,"left":128.5},"7f3281dc-d6b5-44a4":{"x":128.5,"y":214.78125,"width":546,"height":90,"top":214.78125,"right":674.5,"bottom":304.78125,"left":128.5},"7b9cef30-660c-4e16":{"x":128.5,"y":214.78125,"width":90,"height":90,"top":214.78125,"right":218.5,"bottom":304.78125,"left":128.5},"05977613-36f6-4fd2":{"x":128.5,"y":214.78125,"width":90,"height":90,"top":214.78125,"right":218.5,"bottom":304.78125,"left":128.5},"16e62b91-115d-4e3c":{"x":218.5,"y":214.78125,"width":456,"height":90,"top":214.78125,"right":674.5,"bottom":304.78125,"left":218.5},"78711c75-2220-485d":{"x":238.5,"y":214.78125,"width":426,"height":51.921875,"top":214.78125,"right":664.5,"bottom":266.703125,"left":238.5},"b1ec447f-21ad-4773":{"x":238.5,"y":214.78125,"width":426,"height":43.921875,"top":214.78125,"right":664.5,"bottom":258.703125,"left":238.5},"b791c216-80a8-41c6":{"x":238.5,"y":214.78125,"width":426,"height":22.53125,"top":214.78125,"right":664.5,"bottom":237.3125,"left":238.5},"f39f7acc-9438-4f27":{"x":238.5,"y":214.78125,"width":426,"height":22.53125,"top":214.78125,"right":664.5,"bottom":237.3125,"left":238.5},"bb5dbcfa-fb2b-43ad":{"x":238.5,"y":241.3125,"width":426,"height":17.390625,"top":241.3125,"right":664.5,"bottom":258.703125,"left":238.5},"e0f76e55-a794-4496":{"x":238.5,"y":241.3125,"width":95.375,"height":17.390625,"top":241.3125,"right":333.875,"bottom":258.703125,"left":238.5},"330a1611-f554-4948":{"x":238.5,"y":241.3125,"width":40,"height":17.390625,"top":241.3125,"right":278.5,"bottom":258.703125,"left":238.5},"74b18544-7c1f-411d":{"x":238.5,"y":241.5,"width":32,"height":17,"top":241.5,"right":270.5,"bottom":258.5,"left":238.5},"98f8c7fb-6d98-44b2":{"x":238.5,"y":241.5,"width":32,"height":17,"top":241.5,"right":270.5,"bottom":258.5,"left":238.5},"bdfe8092-3730-48e8":{"x":278.5,"y":241.3125,"width":55.375,"height":17.390625,"top":241.3125,"right":333.875,"bottom":258.703125,"left":278.5},"1f686aa9-461c-4c32":{"x":278.5,"y":242.3125,"width":55.375,"height":14,"top":242.3125,"right":333.875,"bottom":256.3125,"left":278.5},"b706ddeb-4dc7-4548":{"x":238.5,"y":287.390625,"width":426,"height":17.390625,"top":287.390625,"right":664.5,"bottom":304.78125,"left":238.5},"7db3c514-87bb-4ad5":{"x":238.5,"y":287.390625,"width":138.921875,"height":17.390625,"top":287.390625,"right":377.421875,"bottom":304.78125,"left":238.5},"c5766042-62fd-4103":{"x":674.5,"y":214.78125,"width":546,"height":90,"top":214.78125,"right":1220.5,"bottom":304.78125,"left":674.5},"de67622f-2b1e-4ff9":{"x":674.5,"y":214.78125,"width":546,"height":46.828125,"top":214.78125,"right":1220.5,"bottom":261.609375,"left":674.5},"07c5d20a-b108-46e6":{"x":811,"y":214.78125,"width":136.5,"height":46.828125,"top":214.78125,"right":947.5,"bottom":261.609375,"left":811},"9a8b5b87-0a5a-4897":{"x":811,"y":218.046875,"width":80,"height":40.296875,"top":218.046875,"right":891,"bottom":258.34375,"left":811},"c6d06533-4a9e-4bc1":{"x":811,"y":218.046875,"width":80,"height":40.296875,"top":218.046875,"right":891,"bottom":258.34375,"left":811},"e389e1d4-c81e-4805":{"x":811,"y":218.046875,"width":80,"height":40.296875,"top":218.046875,"right":891,"bottom":258.34375,"left":811},"4ae62279-ad32-42d6":{"x":811,"y":218.046875,"width":80,"height":40.296875,"top":218.046875,"right":891,"bottom":258.34375,"left":811},"3cb4abcb-8e9e-4293":{"x":811,"y":218.046875,"width":80,"height":20,"top":218.046875,"right":891,"bottom":238.046875,"left":811},"6acdf1cb-ee2e-4c09":{"x":811,"y":218.046875,"width":80,"height":16,"top":218.046875,"right":891,"bottom":234.046875,"left":811},"ffa91051-d20f-43e9":{"x":813.359375,"y":238.046875,"width":75.265625,"height":20.296875,"top":238.046875,"right":888.625,"bottom":258.34375,"left":813.359375},"9c116966-aaaf-4366":{"x":947.5,"y":214.78125,"width":136.5,"height":46.828125,"top":214.78125,"right":1084,"bottom":261.609375,"left":947.5},"2416af45-1cd1-4d9c":{"x":947.5,"y":214.78125,"width":136.5,"height":46.828125,"top":214.78125,"right":1084,"bottom":261.609375,"left":947.5},"bbdeceb5-4dd9-492d":{"x":947.5,"y":214.78125,"width":136.5,"height":44.53125,"top":214.78125,"right":1084,"bottom":259.3125,"left":947.5},"3c904ab6-c00e-44ba":{"x":947.5,"y":214.78125,"width":136.5,"height":43.53125,"top":214.78125,"right":1084,"bottom":258.3125,"left":947.5},"cb5ebfd7-f1e1-49e1":{"x":947.5,"y":214.78125,"width":136.5,"height":43.53125,"top":214.78125,"right":1084,"bottom":258.3125,"left":947.5},"5c9000b1-e24e-40e8":{"x":947.5,"y":214.78125,"width":136.5,"height":22.53125,"top":214.78125,"right":1084,"bottom":237.3125,"left":947.5},"86b76536-b706-407f":{"x":1050.234375,"y":244.3125,"width":21.765625,"height":14,"top":244.3125,"right":1072,"bottom":258.3125,"left":1050.234375},"25e4919c-156e-4437":{"x":1084,"y":218.796875,"width":136.5,"height":38.78125,"top":218.796875,"right":1220.5,"bottom":257.578125,"left":1084},"0ad55a92-e28f-4d18":{"x":1084,"y":218.796875,"width":136.5,"height":38.78125,"top":218.796875,"right":1220.5,"bottom":257.578125,"left":1084},"1a3c1b0c-41de-4ce4":{"x":1084,"y":218.796875,"width":136.5,"height":17.390625,"top":218.796875,"right":1220.5,"bottom":236.1875,"left":1084},"a8748b93-1f4f-4cbe":{"x":1084,"y":218.796875,"width":136.5,"height":17.390625,"top":218.796875,"right":1220.5,"bottom":236.1875,"left":1084},"444b51e8-7ba2-48a8":{"x":1084,"y":240.1875,"width":136.5,"height":17.390625,"top":240.1875,"right":1220.5,"bottom":257.578125,"left":1084},"8d4471c5-152f-40f4":{"x":1084,"y":240.1875,"width":136.5,"height":17.390625,"top":240.1875,"right":1220.5,"bottom":257.578125,"left":1084},"18199ecd-2f95-43ff":{"x":0,"y":314.78125,"width":1349,"height":150.59375,"top":314.78125,"right":1349,"bottom":465.375,"left":0},"e04fec2c-ad0d-494c":{"x":0,"y":344.78125,"width":1349,"height":90.59375,"top":344.78125,"right":1349,"bottom":435.375,"left":0},"c7314697-cb6c-46a5":{"x":0,"y":344.78125,"width":1349,"height":90.59375,"top":344.78125,"right":1349,"bottom":435.375,"left":0},"3658d9e6-7dc2-4bf1":{"x":490,"y":354.78125,"width":369,"height":42.296875,"top":354.78125,"right":859,"bottom":397.078125,"left":490},"770730ff-c702-4cd4":{"x":490,"y":354.78125,"width":369,"height":42.296875,"top":354.78125,"right":859,"bottom":397.078125,"left":490},"e06cea2b-17ff-42a7":{"x":489,"y":354.78125,"width":42,"height":42.296875,"top":354.78125,"right":531,"bottom":397.078125,"left":489},"23c38475-1554-4668":{"x":490,"y":355.78125,"width":40,"height":40.296875,"top":355.78125,"right":530,"bottom":396.078125,"left":490},"4652a160-ec2f-4949":{"x":501.25,"y":366.78125,"width":17.5,"height":17,"top":366.78125,"right":518.75,"bottom":383.78125,"left":501.25},"38aa698b-43f4-4a3b":{"x":530,"y":354.78125,"width":42,"height":42.296875,"top":354.78125,"right":572,"bottom":397.078125,"left":530},"425f00be-113f-4c20":{"x":531,"y":355.78125,"width":40,"height":40.296875,"top":355.78125,"right":571,"bottom":396.078125,"left":531},"79965019-53c4-4174":{"x":546.625,"y":366.78125,"width":8.75,"height":17,"top":366.78125,"right":555.375,"bottom":383.78125,"left":546.625},"6f5b65d6-e057-464c":{"x":571,"y":354.78125,"width":42,"height":42.296875,"top":354.78125,"right":613,"bottom":397.078125,"left":571},"003580b0-40e5-457a":{"x":572,"y":355.78125,"width":40,"height":40.296875,"top":355.78125,"right":612,"bottom":396.078125,"left":572},"baa1a52e-9943-4ab9":{"x":612,"y":354.78125,"width":42,"height":42.296875,"top":354.78125,"right":654,"bottom":397.078125,"left":612},"20245a7f-806a-40ff":{"x":613,"y":355.78125,"width":40,"height":40.296875,"top":355.78125,"right":653,"bottom":396.078125,"left":613},"f9afaa03-67e1-4cb2":{"x":653,"y":354.78125,"width":42,"height":42.296875,"top":354.78125,"right":695,"bottom":397.078125,"left":653},"4b665d0c-f903-488f":{"x":654,"y":355.78125,"width":40,"height":40.296875,"top":355.78125,"right":694,"bottom":396.078125,"left":654},"96d23136-e46c-45a8":{"x":694,"y":354.78125,"width":42,"height":42.296875,"top":354.78125,"right":736,"bottom":397.078125,"left":694},"0c3fc004-8737-423c":{"x":695,"y":355.78125,"width":40,"height":40.296875,"top":355.78125,"right":735,"bottom":396.078125,"left":695},"57835a2d-7baa-46b9":{"x":735,"y":354.78125,"width":42,"height":42.296875,"top":354.78125,"right":777,"bottom":397.078125,"left":735},"db7b03a3-ad95-4007":{"x":736,"y":355.78125,"width":40,"height":40.296875,"top":355.78125,"right":776,"bottom":396.078125,"left":736},"17e43827-2548-473a":{"x":776,"y":354.78125,"width":42,"height":42.296875,"top":354.78125,"right":818,"bottom":397.078125,"left":776},"c04da0c0-23e4-4911":{"x":777,"y":355.78125,"width":40,"height":40.296875,"top":355.78125,"right":817,"bottom":396.078125,"left":777},"ddbbcc9c-b33a-4b4d":{"x":792.625,"y":366.78125,"width":8.75,"height":17,"top":366.78125,"right":801.375,"bottom":383.78125,"left":792.625},"a9e97979-a20c-4227":{"x":817,"y":354.78125,"width":42,"height":42.296875,"top":354.78125,"right":859,"bottom":397.078125,"left":817},"499333c2-0996-49e2":{"x":818,"y":355.78125,"width":40,"height":40.296875,"top":355.78125,"right":858,"bottom":396.078125,"left":818},"104c4d55-6fcc-4d48":{"x":829.25,"y":366.78125,"width":17.5,"height":17,"top":366.78125,"right":846.75,"bottom":383.78125,"left":829.25},"7c945994-fc47-4371":{"x":0,"y":407.078125,"width":1349,"height":20.296875,"top":407.078125,"right":1349,"bottom":427.375,"left":0},"41fce7d3-f5ad-49a7":{"x":634.421875,"y":408.078125,"width":35.40625,"height":17,"top":408.078125,"right":669.828125,"bottom":425.078125,"left":634.421875},"a3fb3bfc-27a7-4f41":{"x":681.625,"y":408.078125,"width":13.421875,"height":17,"top":408.078125,"right":695.046875,"bottom":425.078125,"left":681.625},"2f6c39a8-5916-4d84":{"x":0,"y":465.375,"width":1349,"height":716.125,"top":465.375,"right":1349,"bottom":1181.5,"left":0},"1282f6d0-8c61-489c":{"x":0,"y":465.375,"width":1349,"height":716.125,"top":465.375,"right":1349,"bottom":1181.5,"left":0},"7b707d96-6380-4951":{"x":0,"y":465.375,"width":1349,"height":716.125,"top":465.375,"right":1349,"bottom":1181.5,"left":0},"1b07a597-d537-4344":{"x":104.5,"y":465.375,"width":1140,"height":716.125,"top":465.375,"right":1244.5,"bottom":1181.5,"left":104.5},"40a2c177-a7ec-4f74":{"x":104.5,"y":505.375,"width":1140,"height":421.53125,"top":505.375,"right":1244.5,"bottom":926.90625,"left":104.5},"67113302-e8cb-42f1":{"x":104.5,"y":505.375,"width":1140,"height":421.53125,"top":505.375,"right":1244.5,"bottom":926.90625,"left":104.5},"4d0840c2-b078-43c4":{"x":104.5,"y":505.375,"width":1140,"height":421.53125,"top":505.375,"right":1244.5,"bottom":926.90625,"left":104.5},"2b0f30f0-0d37-4e8f":{"x":104.5,"y":505.375,"width":1140,"height":421.53125,"top":505.375,"right":1244.5,"bottom":926.90625,"left":104.5},"551622a7-f2cd-455c":{"x":92.5,"y":505.375,"width":1164,"height":421.53125,"top":505.375,"right":1256.5,"bottom":926.90625,"left":92.5},"c938799d-e4c4-443e":{"x":124.5,"y":537.375,"width":275,"height":357.53125,"top":537.375,"right":399.5,"bottom":894.90625,"left":124.5},"1a6263c9-0122-4525":{"x":136.5,"y":537.375,"width":251,"height":184.3125,"top":537.375,"right":387.5,"bottom":721.6875,"left":136.5},"664ed6bc-bead-44ff":{"x":136.5,"y":537.375,"width":251,"height":22.53125,"top":537.375,"right":387.5,"bottom":559.90625,"left":136.5},"aa59d9f7-ac8f-402d":{"x":136.5,"y":537.375,"width":251,"height":22.53125,"top":537.375,"right":387.5,"bottom":559.90625,"left":136.5},"286acdc9-dace-4006":{"x":136.5,"y":537.375,"width":251,"height":22.53125,"top":537.375,"right":387.5,"bottom":559.90625,"left":136.5},"404f68ce-95a3-42e3":{"x":136.5,"y":574.90625,"width":251,"height":146.78125,"top":574.90625,"right":387.5,"bottom":721.6875,"left":136.5},"cfb9484c-ad3d-4322":{"x":136.5,"y":574.90625,"width":251,"height":146.78125,"top":574.90625,"right":387.5,"bottom":721.6875,"left":136.5},"e1f04e71-6d20-4e95":{"x":136.5,"y":574.90625,"width":251,"height":146.78125,"top":574.90625,"right":387.5,"bottom":721.6875,"left":136.5},"54f7c591-d387-4ed6":{"x":136.5,"y":574.90625,"width":251,"height":20.296875,"top":574.90625,"right":387.5,"bottom":595.203125,"left":136.5},"a74931d4-d36a-46b7":{"x":136.5,"y":575.90625,"width":105.875,"height":17,"top":575.90625,"right":242.375,"bottom":592.90625,"left":136.5},"0353ed7a-d57a-47c0":{"x":136.5,"y":600.203125,"width":251,"height":20.296875,"top":600.203125,"right":387.5,"bottom":620.5,"left":136.5},"c61f240d-ee4f-465b":{"x":136.5,"y":601.203125,"width":63.09375,"height":17,"top":601.203125,"right":199.59375,"bottom":618.203125,"left":136.5},"22566f8a-e9d0-4337":{"x":136.5,"y":625.5,"width":251,"height":20.296875,"top":625.5,"right":387.5,"bottom":645.796875,"left":136.5},"5aaeb378-f0a1-4e33":{"x":136.5,"y":626.5,"width":59.203125,"height":17,"top":626.5,"right":195.703125,"bottom":643.5,"left":136.5},"29e8321c-de7e-400c":{"x":136.5,"y":650.796875,"width":251,"height":20.296875,"top":650.796875,"right":387.5,"bottom":671.09375,"left":136.5},"6e7f1a56-f20b-44ff":{"x":136.5,"y":651.796875,"width":54.09375,"height":17,"top":651.796875,"right":190.59375,"bottom":668.796875,"left":136.5},"24b948fd-d99e-4a9d":{"x":399.5,"y":537.375,"width":275,"height":357.53125,"top":537.375,"right":674.5,"bottom":894.90625,"left":399.5},"e8eced25-65bb-4afc":{"x":411.5,"y":537.375,"width":251,"height":310.796875,"top":537.375,"right":662.5,"bottom":848.171875,"left":411.5},"9cb1f125-d67e-422d":{"x":411.5,"y":537.375,"width":251,"height":22.53125,"top":537.375,"right":662.5,"bottom":559.90625,"left":411.5},"b5d1f833-9ba3-4883":{"x":411.5,"y":537.375,"width":251,"height":22.53125,"top":537.375,"right":662.5,"bottom":559.90625,"left":411.5},"503d4afc-d5b4-48ce":{"x":411.5,"y":537.375,"width":251,"height":22.53125,"top":537.375,"right":662.5,"bottom":559.90625,"left":411.5},"21fd6df8-9c7e-4fe4":{"x":411.5,"y":574.90625,"width":251,"height":273.265625,"top":574.90625,"right":662.5,"bottom":848.171875,"left":411.5},"222723e3-631f-4238":{"x":411.5,"y":574.90625,"width":251,"height":273.265625,"top":574.90625,"right":662.5,"bottom":848.171875,"left":411.5},"9e270671-d610-4e78":{"x":411.5,"y":574.90625,"width":251,"height":273.265625,"top":574.90625,"right":662.5,"bottom":848.171875,"left":411.5},"fc3b4850-9fde-48a1":{"x":411.5,"y":574.90625,"width":251,"height":20.296875,"top":574.90625,"right":662.5,"bottom":595.203125,"left":411.5},"ea1c12e2-7fab-485e":{"x":411.5,"y":575.90625,"width":66.859375,"height":17,"top":575.90625,"right":478.359375,"bottom":592.90625,"left":411.5},"79b27d12-1e49-45bc":{"x":411.5,"y":600.203125,"width":251,"height":20.296875,"top":600.203125,"right":662.5,"bottom":620.5,"left":411.5},"9583dfd7-d874-4bec":{"x":411.5,"y":601.203125,"width":100.21875,"height":17,"top":601.203125,"right":511.71875,"bottom":618.203125,"left":411.5},"fc1d114f-0a5f-4284":{"x":411.5,"y":625.5,"width":251,"height":20.296875,"top":625.5,"right":662.5,"bottom":645.796875,"left":411.5},"41fa2fc2-3dba-4d14":{"x":411.5,"y":626.5,"width":69.078125,"height":17,"top":626.5,"right":480.578125,"bottom":643.5,"left":411.5},"60fbd2c5-efb4-4aa1":{"x":411.5,"y":650.796875,"width":251,"height":20.296875,"top":650.796875,"right":662.5,"bottom":671.09375,"left":411.5},"d7e56e7e-683b-4049":{"x":411.5,"y":651.796875,"width":138.25,"height":17,"top":651.796875,"right":549.75,"bottom":668.796875,"left":411.5},"de9b56ca-936f-49b7":{"x":674.5,"y":537.375,"width":275,"height":357.53125,"top":537.375,"right":949.5,"bottom":894.90625,"left":674.5},"3b6387c0-b768-4fa9":{"x":686.5,"y":537.375,"width":251,"height":133.71875,"top":537.375,"right":937.5,"bottom":671.09375,"left":686.5},"4523017f-d11f-4e43":{"x":686.5,"y":537.375,"width":251,"height":22.53125,"top":537.375,"right":937.5,"bottom":559.90625,"left":686.5},"b0e11b81-117f-4338":{"x":686.5,"y":537.375,"width":251,"height":22.53125,"top":537.375,"right":937.5,"bottom":559.90625,"left":686.5},"d3e33291-5fab-4c7b":{"x":686.5,"y":537.375,"width":251,"height":22.53125,"top":537.375,"right":937.5,"bottom":559.90625,"left":686.5},"650f9111-30a7-4ac4":{"x":686.5,"y":574.90625,"width":251,"height":96.1875,"top":574.90625,"right":937.5,"bottom":671.09375,"left":686.5},"ce117396-8e47-436a":{"x":686.5,"y":574.90625,"width":251,"height":96.1875,"top":574.90625,"right":937.5,"bottom":671.09375,"left":686.5},"e8634e7c-b25b-4389":{"x":686.5,"y":574.90625,"width":251,"height":96.1875,"top":574.90625,"right":937.5,"bottom":671.09375,"left":686.5},"673580fc-99c7-4dac":{"x":686.5,"y":574.90625,"width":251,"height":20.296875,"top":574.90625,"right":937.5,"bottom":595.203125,"left":686.5},"a37d9b5e-a1b5-4c99":{"x":686.5,"y":575.90625,"width":67.671875,"height":17,"top":575.90625,"right":754.171875,"bottom":592.90625,"left":686.5},"30d789dc-b942-4592":{"x":686.5,"y":600.203125,"width":251,"height":20.296875,"top":600.203125,"right":937.5,"bottom":620.5,"left":686.5},"77addae7-bb76-4cba":{"x":686.5,"y":601.203125,"width":45.984375,"height":17,"top":601.203125,"right":732.484375,"bottom":618.203125,"left":686.5},"c1af4839-31e5-4f98":{"x":686.5,"y":625.5,"width":251,"height":20.296875,"top":625.5,"right":937.5,"bottom":645.796875,"left":686.5},"52aabb85-0054-421f":{"x":686.5,"y":626.5,"width":70.03125,"height":17,"top":626.5,"right":756.53125,"bottom":643.5,"left":686.5},"cc45508e-b4ab-41e4":{"x":686.5,"y":650.796875,"width":251,"height":20.296875,"top":650.796875,"right":937.5,"bottom":671.09375,"left":686.5},"740cd708-4492-495c":{"x":686.5,"y":651.796875,"width":57.75,"height":17,"top":651.796875,"right":744.25,"bottom":668.796875,"left":686.5},"adfbb034-e40f-4925":{"x":949.5,"y":537.375,"width":275,"height":357.53125,"top":537.375,"right":1224.5,"bottom":894.90625,"left":949.5},"25c2038b-3920-4964":{"x":961.5,"y":537.375,"width":251,"height":357.53125,"top":537.375,"right":1212.5,"bottom":894.90625,"left":961.5},"c9e5aaba-7b2c-43a4":{"x":961.5,"y":537.375,"width":251,"height":22.53125,"top":537.375,"right":1212.5,"bottom":559.90625,"left":961.5},"d4f4738c-802d-4fea":{"x":961.5,"y":537.375,"width":251,"height":22.53125,"top":537.375,"right":1212.5,"bottom":559.90625,"left":961.5},"21ad1369-7eb9-41dc":{"x":961.5,"y":537.375,"width":251,"height":22.53125,"top":537.375,"right":1212.5,"bottom":559.90625,"left":961.5},"ca8c730b-8db6-427a":{"x":961.5,"y":574.90625,"width":251,"height":320,"top":574.90625,"right":1212.5,"bottom":894.90625,"left":961.5},"02b2c5cb-27aa-4b53":{"x":961.5,"y":574.90625,"width":251,"height":320,"top":574.90625,"right":1212.5,"bottom":894.90625,"left":961.5},"24bd5eda-e2d1-40f4":{"x":961.5,"y":574.90625,"width":251,"height":48,"top":574.90625,"right":1212.5,"bottom":622.90625,"left":961.5},"ca1cb4ff-e1d2-44c7":{"x":1026.96875,"y":587.8125,"width":120.046875,"height":22.1875,"top":587.8125,"right":1147.015625,"bottom":610,"left":1026.96875},"bb5bfca3-163e-4169":{"x":1179.5,"y":589.90625,"width":16,"height":16,"top":589.90625,"right":1195.5,"bottom":605.90625,"left":1179.5},"8a90d726-7411-4750":{"x":1179.5,"y":589.90625,"width":16,"height":16,"top":589.90625,"right":1195.5,"bottom":605.90625,"left":1179.5},"568610e3-de37-48da":{"x":961.5,"y":638.90625,"width":251,"height":48,"top":638.90625,"right":1212.5,"bottom":686.90625,"left":961.5},"5f669968-43db-47a9":{"x":1045.65625,"y":651.8125,"width":82.6875,"height":22.1875,"top":651.8125,"right":1128.34375,"bottom":674,"left":1045.65625},"12f5fc2b-618c-4d6e":{"x":1179.5,"y":653.90625,"width":16,"height":16,"top":653.90625,"right":1195.5,"bottom":669.90625,"left":1179.5},"273e197a-3c03-4658":{"x":1179.5,"y":653.90625,"width":16,"height":16,"top":653.90625,"right":1195.5,"bottom":669.90625,"left":1179.5}}